ezodf/__init__.py
ezodf/_version.py
ezodf/base.py
ezodf/body.py
ezodf/bytestreammanager.py
ezodf/cells.py
ezodf/cellspancontroller.py
ezodf/compatibility.py
ezodf/conf.py
ezodf/const.py
ezodf/content.py
ezodf/document.py
ezodf/drawingpage.py
ezodf/filemanager.py
ezodf/manifest.py
ezodf/meta.py
ezodf/nodeorganizer.py
ezodf/nodestructurechecker.py
ezodf/nodestructuretags.py
ezodf/observer.py
ezodf/pagecontainer.py
ezodf/pages.py
ezodf/presentationpage.py
ezodf/propertymixins.py
ezodf/protection.py
ezodf/sheets.py
ezodf/styles.py
ezodf/table.py
ezodf/tablecolumncontroller.py
ezodf/tablenormalizer.py
ezodf/tablerowcontroller.py
ezodf/tableutils.py
ezodf/text.py
ezodf/timeparser.py
ezodf/variables.py
ezodf/whitespaces.py
ezodf/wrapcache.py
ezodf/xmlns.py
pyexcel_ezodf-0.3.4.dist-info/DESCRIPTION.rst
pyexcel_ezodf-0.3.4.dist-info/METADATA
pyexcel_ezodf-0.3.4.dist-info/RECORD
pyexcel_ezodf-0.3.4.dist-info/WHEEL
pyexcel_ezodf-0.3.4.dist-info/metadata.json
pyexcel_ezodf-0.3.4.dist-info/top_level.txt
