Metadata-Version: 1.1
Name: pyexcel-ezodf
Version: 0.3.4
Summary: A Python package to create/manipulate OpenDocumentFormat files
Home-page: https://github.com/pyexcel/pyexcel-ezodf
Author: Manfred Moitzi
Author-email: mozman@gmx.at
License: MIT
Download-URL: https://github.com/pyexcel/pyexcel-ezodf/archive/0.3.4.tar.gz
Keywords: ODF,OpenDocumentFormat,OpenOffice LibreOffice,python
Platform: UNKNOWN
Classifier: Topic :: Office/Business
Classifier: Topic :: Utilities
Classifier: Topic :: Software Development :: Libraries
Classifier: Programming Language :: Python
Classifier: Intended Audience :: Developers
Classifier: Programming Language :: Python :: 2.6
Classifier: Programming Language :: Python :: 2.7
Classifier: Programming Language :: Python :: 3.3
Classifier: Programming Language :: Python :: 3.4
Classifier: Programming Language :: Python :: 3.5
Classifier: Programming Language :: Python :: 3.6
Classifier: License :: OSI Approved :: MIT License
Classifier: Development Status :: 3 - Alpha
Classifier: Operating System :: OS Independent
Classifier: Topic :: Office/Business :: Office Suites
